twittersent/__init__.py
twittersent/client.py
twittersent-0.0.2.dist-info/DESCRIPTION.rst
twittersent-0.0.2.dist-info/METADATA
twittersent-0.0.2.dist-info/RECORD
twittersent-0.0.2.dist-info/WHEEL
twittersent-0.0.2.dist-info/metadata.json
twittersent-0.0.2.dist-info/top_level.txt
