Metadata-Version: 2.0
Name: twittersent
Version: 0.0.2
Summary: A python package to analyse the tweets and extract meaning from the data, can be installed with pip.
Home-page: https://github.com/ekchusis/twittersent
Author: Shekhar Jha
Author-email: shekhar09jha@gmail.com
License: BSD
Download-URL: https://github.com/ekchusis/twittersent/tarball/0.0.2
Platform: UNKNOWN
Classifier: Development Status :: 3 - Alpha
Classifier: License :: OSI Approved :: BSD License
Classifier: Intended Audience :: Developers
Classifier: Programming Language :: Python :: 3
Classifier: Programming Language :: Python :: 3.5
Requires-Dist: python-twitter
Requires-Dist: seaborn
Requires-Dist: pandas
Requires-Dist: textblob
